dictionary/__init__.py
dictionary/dictionary.py
ci_cd_elham-2.0.0.dist-info/METADATA
ci_cd_elham-2.0.0.dist-info/WHEEL
ci_cd_elham-2.0.0.dist-info/top_level.txt
ci_cd_elham-2.0.0.dist-info/RECORD
