Metadata-Version: 2.1
Name: ci-cd-elham
Version: 2.0.0
Summary: UNKNOWN
Author: Elham Amin
License: UNKNOWN
Platform: UNKNOWN
Requires-Python: >=3.8
Requires-Dist: requests (>=2.23.0)
